toggl_to_sqlite/__init__.py
toggl_to_sqlite/_version.py
toggl_to_sqlite/cli.py
toggl_to_sqlite/utils.py
toggl_to_sqlite-0.9.0.dist-info/METADATA
toggl_to_sqlite-0.9.0.dist-info/WHEEL
toggl_to_sqlite-0.9.0.dist-info/entry_points.txt
toggl_to_sqlite-0.9.0.dist-info/licenses/LICENSE
toggl_to_sqlite-0.9.0.dist-info/RECORD
