Metadata-Version: 2.4
Name: toggl-to-sqlite
Version: 0.9.0
Summary: Create a SQLite database containing data from your Toggl account
Project-URL: Issues, https://github.com/ryancheley/toggl-to-sqlite/issues
Project-URL: CI, https://github.com/ryancheley/toggl-to-sqlite/actions
Project-URL: Changelog, https://github.com/ryancheley/toggl-to-sqlite/releases
Project-URL: Documentation, https://github.com/ryancheley/toggl-to-sqlite/blob/main/README.md
Author: Ryan Cheley
License: Apache-2.0
License-File: LICENSE
Classifier: Development Status :: 4 - Beta
Classifier: Intended Audience :: Developers
Classifier: Programming Language :: Python :: 3.9
Classifier: Programming Language :: Python :: 3.10
Classifier: Programming Language :: Python :: 3.11
Classifier: Programming Language :: Python :: 3.12
Classifier: Programming Language :: Python :: 3.13
Classifier: Topic :: Utilities
Requires-Python: >=3.9
Requires-Dist: click
Requires-Dist: packaging>=25.0
Requires-Dist: requests
Requires-Dist: requests-mock
Requires-Dist: sqlite-utils>=2.4.4
Requires-Dist: toml
Provides-Extra: test
Requires-Dist: cogapp; extra == 'test'
Requires-Dist: coverage; extra == 'test'
Requires-Dist: mypy; extra == 'test'
Requires-Dist: pre-commit; extra == 'test'
Requires-Dist: pytest; extra == 'test'
Requires-Dist: ruff; extra == 'test'
